setup.cfg
setup.py
plugin/__init__.py
plugin/pep8linter.py
ulint_pep8.egg-info/PKG-INFO
ulint_pep8.egg-info/SOURCES.txt
ulint_pep8.egg-info/dependency_links.txt
ulint_pep8.egg-info/entry_points.txt
ulint_pep8.egg-info/requires.txt
ulint_pep8.egg-info/top_level.txt