Metadata-Version: 1.1
Name: ulint-pep8
Version: 0.2
Summary: PEP8 linter for ulint
Home-page: http://packages.python.org/ulint-pep8
Author: Thibault Saunier
Author-email: tsaunier@gnome.org
License: LGPL
Keywords: lint plugin pep8
Platform: UNKNOWN
Classifier: Topic :: Utilities
Classifier: License :: OSI Approved :: GNU Lesser General Public License v2 (LGPLv2) 
